jpegio-0.2.8.dist-info/top_level.txt
jpegio-0.2.8.dist-info/LICENSE
jpegio-0.2.8.dist-info/WHEEL
jpegio-0.2.8.dist-info/RECORD
jpegio-0.2.8.dist-info/METADATA
jpegio/componentinfo.pyx
jpegio/flags.py
jpegio/componentinfo.pxd
jpegio/__init__.py
jpegio/clibjpeg.pxd
jpegio/jstruct.pxd
jpegio/decompressedjpeg.pyx
jpegio/mat2D.h
jpegio/jstruct.h
jpegio/io.py
jpegio/decompressedjpeg.cpython-39-x86_64-linux-gnu.so
jpegio/decompressedjpeg.pxd
jpegio/componentinfo.cpython-39-x86_64-linux-gnu.so
