Metadata-Version: 1.0
Name: jpegio
Version: 0.2.8
Summary: A python package for accessing the internal variables of JPEG file format.
Home-page: http://github.com/eldritchjs/jpegio
Author: EldritchJS
Author-email: jschlessman@gmail.com
License: Apache License 2.0
Platform: UNKNOWN
